setup.cfg
setup.py
matialvarezs_node_accounts/__init__.py
matialvarezs_node_accounts/admin.py
matialvarezs_node_accounts/apps.py
matialvarezs_node_accounts/context_processors.py
matialvarezs_node_accounts/decorators.py
matialvarezs_node_accounts/definitions.py
matialvarezs_node_accounts/dispatcher.py
matialvarezs_node_accounts/errors.py
matialvarezs_node_accounts/managers.py
matialvarezs_node_accounts/middlewares.py
matialvarezs_node_accounts/models.py
matialvarezs_node_accounts/serializers.py
matialvarezs_node_accounts/settings.py
matialvarezs_node_accounts/signals.py
matialvarezs_node_accounts/tests.py
matialvarezs_node_accounts/urls.py
matialvarezs_node_accounts/utils.py
matialvarezs_node_accounts/views.py
matialvarezs_node_accounts.egg-info/PKG-INFO
matialvarezs_node_accounts.egg-info/SOURCES.txt
matialvarezs_node_accounts.egg-info/dependency_links.txt
matialvarezs_node_accounts.egg-info/top_level.txt
matialvarezs_node_accounts/management/__init__.py
matialvarezs_node_accounts/management/commands/__init__.py
matialvarezs_node_accounts/management/commands/matialvarezs_node_accounts_test_command.py
matialvarezs_node_accounts/migrations/__init__.py