Metadata-Version: 1.1
Name: matialvarezs-node-accounts
Version: 0.0.1
Summary: Nodes accounts - create user api and get token
Home-page: UNKNOWN
Author: Matias Alvarez Sabate
Author-email: matialvarezs@gmail.com
License: UNKNOWN
Platform: UNKNOWN
Classifier: Programming Language :: Python :: 3.5
